Metadata-Version: 2.1
Name: nptweak
Version: 0.1.0
Summary: utility functions for numpy
Home-page: http://github.com/kmedian/nptweak
Author: Ulf Hamster
Author-email: 554c46@gmail.com
License: MIT
Platform: UNKNOWN
Requires-Python: >=3.7
